pg_db_operation_mcp_server/__init__.py
pg_db_operation_mcp_server/server.py
pg_db_operation_mcp_server-0.2.0.dist-info/METADATA
pg_db_operation_mcp_server-0.2.0.dist-info/WHEEL
pg_db_operation_mcp_server-0.2.0.dist-info/entry_points.txt
pg_db_operation_mcp_server-0.2.0.dist-info/RECORD
