Metadata-Version: 2.4
Name: pg-db-operation-mcp-server
Version: 0.2.0
Summary: Add your description here
Author-email: lishuang <lishuang@microconnect.com>
Requires-Python: >=3.10
Requires-Dist: bs4>=0.0.2
Requires-Dist: dashscope>=1.24.0
Requires-Dist: dotenv>=0.9.9
Requires-Dist: httpx>=0.28.1
Requires-Dist: mcp[cli]>=1.12.2
Requires-Dist: psycopg2>=2.9.10
Requires-Dist: pymysql>=1.1.1
